zoomy/__init__.py
zoomy/zoomy.py
zoomy-0.5.dist-info/METADATA
zoomy-0.5.dist-info/WHEEL
zoomy-0.5.dist-info/entry_points.txt
zoomy-0.5.dist-info/top_level.txt
zoomy-0.5.dist-info/RECORD
