Metadata-Version: 2.1
Name: zoomy
Version: 0.5
Summary: A Zoom utility for the terminal
Home-page: https://github.com/kewbish/zoomy
Author: Kewbish
Author-email: kewbish@gmail.com
License: UNKNOWN
Platform: UNKNOWN
Classifier: Programming Language :: Python :: 3
Classifier: License :: OSI Approved :: GNU General Public License v3 (GPLv3)
Classifier: Operating System :: OS Independent
Classifier: Intended Audience :: Education
